<?xml version="1.0" encoding="utf-8"?>
<Works>
  <Work>
    <Author>Ю. В. Коваль, А. Б. Ставровський</Author>
    <WorkName>Інформаційні мережі: навчальний посібник</WorkName>
    <Faculty>Факультет комп'ютерних наук та кібернетики</Faculty>
    <Department>Кафедра теоретичної кібернетики</Department>
    <WorkType>Посібник</WorkType>
    <Year>2021</Year>
  </Work>
  <Work>
    <Author>С.В. Денисов, В.В. Семенов</Author>
    <WorkName>Методи першого порядку для  задач узагальненого оптимального керування системами з розподіленими параметрами.</WorkName>
    <Faculty>Факультет комп'ютерних наук та кібернетики</Faculty>
    <Department>Кафедра обчислювальної математики</Department>
    <WorkType>Публікація</WorkType>
    <Year>2020</Year>
  </Work>
  <Work>
    <Author>С. С. Шкільняк</Author>
    <WorkName>Математична логіка. Приклади і задачі: Навчальний посібник.</WorkName>
    <Faculty>Факультет комп'ютерних наук та кібернетики</Faculty>
    <Department>Кафедра теорії та технології програмування</Department>
    <WorkType>Посібник</WorkType>
    <Year>2007</Year>
  </Work>
  <Work>
    <Author>І.В. Самойленко, А.В. Нікітін.</Author>
    <WorkName>Аналіз асимптотичних властивостей еволюційних рівнянь з випадковим впливом в умовах пуассонової апроксимації.</WorkName>
    <Faculty>Факультет комп'ютерних наук та кібернетики</Faculty>
    <Department>Кафедра дослідження операцій</Department>
    <WorkType>Монографія</WorkType>
    <Year>2020</Year>
  </Work>
  <Work>
    <Author>В.І.Сущанський, В.С.Сікора</Author>
    <WorkName>Операції на групах підстановок: теорія і застосування.</WorkName>
    <Faculty>Механіко-математичний факультет</Faculty>
    <Department>Кафедра алгебри і комп'ютерної математики</Department>
    <WorkType>Монографія</WorkType>
    <Year>2003</Year>
  </Work>
  <Work>
    <Author>О. О. Курченко</Author>
    <WorkName>Диференціальне числення функції однієї змінної</WorkName>
    <Faculty>Механіко-математичний факультет</Faculty>
    <Department>Кафедра математичного аналізу</Department>
    <WorkType>Підручник</WorkType>
    <Year>2022</Year>
  </Work>
  <Work>
    <Author>В. Ф. Коваленко, І. М. Халімонова, Н. П. Харченко, В. М. Стецюк</Author>
    <WorkName>Загальна фізика у прикладах, запитаннях і відповідях.</WorkName>
    <Faculty>Факультет радіофізики, електроніки ти комп'ютерних систем</Faculty>
    <Department>Кафедра математики та теоретичної радіофізики</Department>
    <WorkType>Підручник</WorkType>
    <Year>2012</Year>
  </Work>
  <Work>
    <Author>В. П. Сохацький,  М. В. Петричук</Author>
    <WorkName>Комп’ютерні технології у фізиці. Методики моделювання магнітних, електричних та оптичних явищ у тонкошарових, об’ємних та композитних структура</WorkName>
    <Faculty>Факультет радіофізики, електроніки ти комп'ютерних систем</Faculty>
    <Department>Кафедра комп'ютерної інженерії</Department>
    <WorkType>Посібник</WorkType>
    <Year>2021</Year>
  </Work>
  <Work>
    <Author> Ф.Г. Гаращенко, В.Т. Матвієнко, І.І. Харченко</Author>
    <WorkName>Моделювання динаміки заряджених пучків як задача практичної стійкості в оптимізаційній постановці.</WorkName>
    <Faculty>Факультет комп'ютерних наук та кібернетики</Faculty>
    <Department>Кафедра модулювання складних систем</Department>
    <WorkType>Публікація</WorkType>
    <Year>2012</Year>
  </Work>
  <Work>
    <Author>С.С. Шкільняк, М.С. Нікітченко</Author>
    <WorkName>Композиційно-номінативні логіки над ієрархічними даними</WorkName>
    <Faculty>Факультет комп'ютерних наук та кібернетики</Faculty>
    <Department>Кафедра теорії та технології програмування</Department>
    <WorkType>Публікація</WorkType>
    <Year>2010</Year>
  </Work>
</Works>
